{"top_builds": [[{"talent1": "StitchesMasteryHeavySlam", "talent4": "StitchesMasteryPutridGroundSlam", "talent7": "StitchesToxicGas", "talent10": "StitchesHeroicAbilityGorge", "talent13": "StitchesMasteryMegaSmashSlam", "talent16": "StitchesMasteryPulverizeSlam", "talent20": "StitchesMasteryHungryHungryStitchesGorge"}, {"total_games": 752, "wins": 454}, 4.5161106657950025e-09], [{"talent1": "StitchesMasteryHeavySlam", "talent4": "StitchesMasteryPutridGroundSlam", "talent7": "StitchesToxicGas", "talent10": "StitchesHeroicAbilityPutridBile", "talent13": "StitchesMasteryMegaSmashSlam", "talent16": "StitchesMasteryPulverizeSlam", "talent20": "GenericTalentHardenedShield"}, {"total_games": 1027, "wins": 642}, 1.2723851706731543e-16], [{"talent1": "StitchesMasteryHeavySlam", "talent4": "StitchesMasteryPutridGroundSlam", "talent7": "StitchesToxicGas", "talent10": "StitchesHeroicAbilityGorge", "talent13": "StitchesMasteryMegaSmashSlam", "talent16": "StitchesMasteryPulverizeSlam", "talent20": "StitchesCannibalize"}, {"total_games": 387, "wins": 258}, 2.1187017838967458e-11], [{"talent1": "StitchesMasteryHeavySlam", "talent4": "StitchesMasteryPutridGroundSlam", "talent7": "StitchesToxicGas", "talent10": "StitchesHeroicAbilityPutridBile", "talent13": "StitchesMasteryMegaSmashSlam", "talent16": "StitchesMasteryPulverizeSlam", "talent20": "StitchesCannibalize"}, {"total_games": 546, "wins": 365}, 6.364057073173935e-16], [{"talent1": "GenericDampenMagic", "talent4": "StitchesMasteryPutridGroundSlam", "talent7": "StitchesToxicGas", "talent10": "StitchesHeroicAbilityPutridBile", "talent13": "StitchesMasteryMegaSmashSlam", "talent16": "StitchesMasteryPulverizeSlam", "talent20": "GenericTalentHardenedShield"}, {"total_games": 265, "wins": 186}, 1.59566650028738e-11], [{"talent1": "StitchesMasteryHeavySlam", "talent4": "StitchesMasteryPutridGroundSlam", "talent7": "StitchesToxicGas", "talent10": "StitchesHeroicAbilityPutridBile", "talent13": "StitchesMasteryMegaSmashSlam", "talent16": "StitchesMasteryPulverizeSlam", "talent20": "StitchesPotentBile"}, {"total_games": 1645, "wins": 1161}, 6.736353768955391e-68], [{"talent1": "StitchesHungryforMore", "talent4": "GenericTalentAmplifiedHealing", "talent7": "StitchesMasterySavorTheFlavorDevour", "talent10": "StitchesHeroicAbilityPutridBile", "talent13": "StitchesFleaBag", "talent16": "StitchesMasteryFishingHook", "talent20": "StitchesCannibalize"}, {"total_games": 189, "wins": 134}, 5.097940744048712e-09], [{"talent1": "StitchesHungryforMore", "talent4": "GenericTalentAmplifiedHealing", "talent7": "StitchesMasterySavorTheFlavorDevour", "talent10": "StitchesHeroicAbilityPutridBile", "talent13": "StitchesMasteryIndigestionDevour", "talent16": "StitchesMasteryFishingHook", "talent20": "StitchesPotentBile"}, {"total_games": 204, "wins": 147}, 1.3471687304978748e-10], [{"talent1": "GenericDampenMagic", "talent4": "StitchesMasteryPutridGroundSlam", "talent7": "StitchesToxicGas", "talent10": "StitchesHeroicAbilityPutridBile", "talent13": "StitchesMasteryMegaSmashSlam", "talent16": "StitchesMasteryPulverizeSlam", "talent20": "StitchesPotentBile"}, {"total_games": 168, "wins": 123}, 8.194107623762825e-10], [{"talent1": "StitchesMasteryHeavySlam", "talent4": "StitchesMasteryPutridGroundSlam", "talent7": "StitchesToxicGas", "talent10": "StitchesHeroicAbilityPutridBile", "talent13": "StitchesMasteryIndigestionDevour", "talent16": "StitchesMasteryPulverizeSlam", "talent20": "StitchesPotentBile"}, {"total_games": 128, "wins": 100}, 5.6817453486540153e-11]]}